latency_watch/__init__.py
latency_watch/profiler.py
latency_watch/trace_config.py
latencywatch-0.2.0.dist-info/licenses/LICENCE
tests/__init__.py
tests/run_all_tests.py
tests/test1.py
tests/test_basic_hierarchy.py
tests/test_include_exclude.py
tests/test_max_depth.py
tests/test_min_duration.py
tests/test_root_only.py
latencywatch-0.2.0.dist-info/METADATA
latencywatch-0.2.0.dist-info/WHEEL
latencywatch-0.2.0.dist-info/top_level.txt
latencywatch-0.2.0.dist-info/RECORD
