Metadata-Version: 2.4
Name: latencywatch
Version: 0.2.0
Summary: A lightweight Python profiler using sys.setprofile for latency tracing
Home-page: https://github.com/NAGARAJ08/latencywatch
Author: Nagaraj K   
Author-email: kbnagaraj18@gmail.com
Classifier: Programming Language :: Python :: 3
Classifier: Operating System :: OS Independent
Classifier: License :: OSI Approved :: MIT License
Requires-Python: >=3.6
License-File: LICENCE
Dynamic: author
Dynamic: author-email
Dynamic: classifier
Dynamic: description
Dynamic: description-content-type
Dynamic: home-page
Dynamic: license-file
Dynamic: requires-python
Dynamic: summary
